openg2p_spar_g2pconnect_mapper_connector_lib/__init__.py
openg2p_spar_g2pconnect_mapper_connector_lib/app.py
openg2p_spar_g2pconnect_mapper_connector_lib/config.py
openg2p_spar_g2pconnect_mapper_connector_lib/connector.py
openg2p_spar_g2pconnect_mapper_connector_lib/helper.py
openg2p_spar_g2pconnect_mapper_connector_lib-1.1.0.dist-info/METADATA
openg2p_spar_g2pconnect_mapper_connector_lib-1.1.0.dist-info/WHEEL
openg2p_spar_g2pconnect_mapper_connector_lib-1.1.0.dist-info/licenses/LICENSE
openg2p_spar_g2pconnect_mapper_connector_lib-1.1.0.dist-info/RECORD
