Metadata-Version: 2.4
Name: openg2p-spar-g2pconnect-mapper-connector-lib
Version: 1.1.0
Summary: OpenG2P SPAR Self Service G2PConnect Mapper Connector Library
Project-URL: Homepage, https://openg2p.org
Project-URL: Documentation, https://docs.openg2p.org/
Project-URL: Repository, https://github.com/OpenG2P/openg2p-spar-self-service
Project-URL: Source, https://github.com/OpenG2P/openg2p-spar-self-service
Author-email: OpenG2P <info@openg2p.org>
License-File: LICENSE
Classifier: License :: OSI Approved :: Mozilla Public License 2.0 (MPL 2.0)
Classifier: Operating System :: OS Independent
Classifier: Programming Language :: Python :: 3
Requires-Python: >=3.7
Requires-Dist: openg2p-spar-mapper-interface-lib
Requires-Dist: pyjwt
